MANIFEST.in
README.rst
mongooplog_alt.py
setup.cfg
setup.py
mongooplog_alt.egg-info/PKG-INFO
mongooplog_alt.egg-info/SOURCES.txt
mongooplog_alt.egg-info/dependency_links.txt
mongooplog_alt.egg-info/entry_points.txt
mongooplog_alt.egg-info/requires.txt
mongooplog_alt.egg-info/top_level.txt