Metadata-Version: 1.1
Name: mongooplog-alt
Version: 0.4.2
Summary: Improved alternative to official mongooplog utility.
Home-page: https://github.com/asivokon/mongooplog-alt
Author: Aleksey Sivokon
Author-email: aleksey.sivokon@gmail.com
License: http://www.apache.org/licenses/LICENSE-2.0.html
Download-URL: http://github.com/asivokon/mongooplog-alt/archive/0.4.2.tar.gz
Keywords: mongodb,mongo,oplog,mongooplog
Platform: any
Classifier: Development Status :: 4 - Beta
Classifier: Intended Audience :: Developers
Classifier: License :: OSI Approved :: Apache Software License
Classifier: Programming Language :: Python
Classifier: Topic :: Database
Classifier: Topic :: Software Development :: Libraries :: Python Modules
Classifier: Operating System :: OS Independent
